solana_agent/__init__.py
solana_agent/adapters/__init__.py
solana_agent/adapters/mongodb_adapter.py
solana_agent/adapters/openai_adapter.py
solana_agent/cli.py
solana_agent/client/__init__.py
solana_agent/client/solana_agent.py
solana_agent/domains/__init__.py
solana_agent/domains/agent.py
solana_agent/domains/routing.py
solana_agent/factories/__init__.py
solana_agent/factories/agent_factory.py
solana_agent/guardrails/pii.py
solana_agent/interfaces/__init__.py
solana_agent/interfaces/client/client.py
solana_agent/interfaces/guardrails/guardrails.py
solana_agent/interfaces/plugins/plugins.py
solana_agent/interfaces/providers/__init__.py
solana_agent/interfaces/providers/data_storage.py
solana_agent/interfaces/providers/llm.py
solana_agent/interfaces/providers/memory.py
solana_agent/interfaces/services/agent.py
solana_agent/interfaces/services/query.py
solana_agent/interfaces/services/routing.py
solana_agent/plugins/__init__.py
solana_agent/plugins/manager.py
solana_agent/plugins/registry.py
solana_agent/plugins/tools/__init__.py
solana_agent/plugins/tools/auto_tool.py
solana_agent/repositories/__init__.py
solana_agent/repositories/memory.py
solana_agent/services/__init__.py
solana_agent/services/agent.py
solana_agent/services/query.py
solana_agent/services/routing.py
solana_agent-33.1.1.dist-info/METADATA
solana_agent-33.1.1.dist-info/WHEEL
solana_agent-33.1.1.dist-info/entry_points.txt
solana_agent-33.1.1.dist-info/licenses/LICENSE
solana_agent-33.1.1.dist-info/RECORD
