Metadata-Version: 2.4
Name: solana-agent
Version: 33.1.1
Summary: AI Agents for Solana
License: MIT
License-File: LICENSE
Keywords: solana,solana ai,solana agent,ai,ai agent,ai agents
Author: Bevan Hunt
Author-email: bevan@bevanhunt.com
Requires-Python: >=3.13,<3.14
Classifier: Development Status :: 5 - Production/Stable
Classifier: Intended Audience :: Developers
Classifier: License :: OSI Approved :: MIT License
Classifier: Programming Language :: Python :: 3
Classifier: Programming Language :: Python :: 3.13
Classifier: Topic :: Scientific/Engineering :: Artificial Intelligence
Requires-Dist: logfire (>=4.16.0,<5.0.0)
Requires-Dist: openai (>=2.11.0,<3.0.0)
Requires-Dist: pillow (>=12.0.0,<13.0.0)
Requires-Dist: pydantic (>=2)
Requires-Dist: pymongo (>=4.15.5,<5.0.0)
Requires-Dist: rich (>=13,<14.0)
Requires-Dist: scrubadub (>=2.0.1,<3.0.0)
Requires-Dist: typer (>=0.20.0,<0.21.0)
Requires-Dist: websockets (>=13,<16)
Requires-Dist: zep-cloud (>=3.13.0,<4.0.0)
Project-URL: Documentation, https://docs.solana-agent.com
Project-URL: Homepage, https://solana-agent.com
Project-URL: Repository, https://github.com/truemagic-coder/solana-agent
